dhicn_accident_management_service/__init__.py
dhicn_accident_management_service/api_client.py
dhicn_accident_management_service/configuration.py
dhicn_accident_management_service/exceptions.py
dhicn_accident_management_service/rest.py
dhicn_accident_management_service/api/__init__.py
dhicn_accident_management_service/api/accident_api.py
dhicn_accident_management_service/api/component_api.py
dhicn_accident_management_service/api/event_api.py
dhicn_accident_management_service/api/scene_api.py
dhicn_accident_management_service/api/time_series_api.py
dhicn_accident_management_service/models/__init__.py
dhicn_accident_management_service/models/accident_detail_info.py
dhicn_accident_management_service/models/accident_detail_input.py
dhicn_accident_management_service/models/accident_info.py
dhicn_accident_management_service/models/accident_level_enum.py
dhicn_accident_management_service/models/accident_type_enum.py
dhicn_accident_management_service/models/add_accident_input.py
dhicn_accident_management_service/models/add_component_input.py
dhicn_accident_management_service/models/add_component_key_input.py
dhicn_accident_management_service/models/add_component_value_input.py
dhicn_accident_management_service/models/add_event_input.py
dhicn_accident_management_service/models/add_scene_input.py
dhicn_accident_management_service/models/add_ts_input.py
dhicn_accident_management_service/models/business_type_enum.py
dhicn_accident_management_service/models/component_detail_info.py
dhicn_accident_management_service/models/component_detail_input.py
dhicn_accident_management_service/models/component_info.py
dhicn_accident_management_service/models/component_key_info.py
dhicn_accident_management_service/models/component_value_info.py
dhicn_accident_management_service/models/discharge_type_enum.py
dhicn_accident_management_service/models/event_detail_info.py
dhicn_accident_management_service/models/event_detail_input.py
dhicn_accident_management_service/models/event_info.py
dhicn_domain_paas_sdk_python-1.0.17.dist-info/LICENSE
dhicn_domain_paas_sdk_python-1.0.17.dist-info/METADATA
dhicn_domain_paas_sdk_python-1.0.17.dist-info/WHEEL
dhicn_domain_paas_sdk_python-1.0.17.dist-info/top_level.txt
dhicn_domain_paas_sdk_python-1.0.17.dist-info/RECORD
