Metadata-Version: 2.1
Name: dhicn-domain-paas-sdk-python
Version: 1.0.17
Summary: UNKNOWN
Home-page: https://github.com/DHICN/Domain-Paas-SDK-Python
Author: dhi
Author-email: wafe@dhigroup.com
License: MIT
Keywords: sdk,python,domain-paas
Platform: UNKNOWN
Requires-Dist: urllib3>=1.15
Requires-Dist: six>=1.10
Requires-Dist: certifi
Requires-Dist: python-dateutil
